<?xml version="1.0" encoding="UTF-8"?>

<!--
 * See the NOTICE file distributed with this work for additional
 * information regarding copyright ownership.
 *
 * This program is free software: you can redistribute it and/or modify
 * it under the terms of the GNU Affero General Public License as published by
 * the Free Software Foundation, either version 3 of the License, or
 * (at your option) any later version.
 *
 * This program is distributed in the hope that it will be useful,
 * but WITHOUT ANY WARRANTY; without even the implied warranty of
 * MERCHANTABILITY or FITNESS FOR A PARTICULAR PURPOSE.  See the
 * GNU Affero General Public License for more details.
 *
 * You should have received a copy of the GNU Affero General Public License
 * along with this program.  If not, see http://www.gnu.org/licenses/
-->

<xwikidoc version="1.1">
  <web>PhenoTips</web>
  <name>CreatePatientRecordForm</name>
  <language/>
  <defaultLanguage/>
  <translation>0</translation>
  <creator>xwiki:XWiki.Admin</creator>
  <creationDate>1401822210000</creationDate>
  <parent>PhenoTips.WebHome</parent>
  <author>xwiki:XWiki.Admin</author>
  <contentAuthor>xwiki:XWiki.Admin</contentAuthor>
  <date>1442436659000</date>
  <contentUpdateDate>1442431648000</contentUpdateDate>
  <version>1.1</version>
  <title>Form for creating new patient records</title>
  <comment/>
  <minorEdit>false</minorEdit>
  <syntaxId>xwiki/2.1</syntaxId>
  <hidden>true</hidden>
  <content>{{velocity}}{{html clean=false}}
$xwiki.ssx.use('PhenoTips.Widgets')##
$xwiki.jsx.use('PhenoTips.Widgets')##
#if ($xwiki.hasAccessLevel('edit', "data.$!{reservedDocumentName}"))
  &lt;form id="patient-creation-form" class="patient-creation-form x-single-submit-form" action="$xwiki.getURL('PhenoTips.CreatePatientRecord')" method="post"&gt;&lt;div&gt;
    &lt;input type="hidden" name="form_token" value="$!{services.csrf.getToken()}" /&gt;
    &lt;input type="hidden" name="doCreate" value="1" /&gt;
    ##
    #if ($xwiki.exists('PhenoTips.StudyBindingClass'))
      ## Is there more than one sheet option?
      ## Check out all the groups this user is part of
      #set ($studiesVisibilityPreference = $xwiki.getDocument('XWiki.XWikiPreferences').getObject('XWiki.ConfigurationClass', 'property', 'study-visibility-option', false).getProperty('value').value)
      #if ($studiesVisibilityPreference == 'unrestricted')
        #set ($studyClassName = 'PhenoTips.StudyClass')
        #set ($studyTemplateName = 'PhenoTips.StudyTemplate')
        #set ($query = $services.query.xwql("from doc.object(${studyClassName}) as std where doc.fullName &lt;&gt; :template").bindValue('template', $studyTemplateName))
        #set ($studyDocs = $xwiki.wrapDocs($query.execute()))
        #set ($studies = $collectionstool.sortedSet)
        #foreach ($study in $studyDocs)
          #set ($discard = $studies.add($services.model.serialize($study.documentReference, 'default')))
        #end
      #else
        #set ($toProcess = $collectionstool.queue)
        #set ($discard = $toProcess.add($xcontext.userReference.toString()))
        #set ($groups = [])
        #set ($studies = $collectionstool.sortedSet)
        #foreach ($iteration in [0..1000])
          #if ($toProcess.empty)
            #break
          #end
          #set ($item = $toProcess.poll())
          #foreach ($group in $xwiki.wrapDocs($xwiki.rightsmanager.getAllGroupsNamesForMember($item)))
            #set ($groupObj = $group.getObject('PhenoTips.PhenoTipsGroupClass'))
            #if (!$groupObj &amp;&amp; $group.documentReference.name.endsWith(' Administrators'))
              #set ($groupObj = $xwiki.getDocument($services.model.resolveDocument($stringtool.removeEnd($group.documentReference.name, ' Administrators'), $group.documentReference.parent)).getObject('PhenoTips.PhenoTipsGroupClass'))
            #end
            #if ($groupObj &amp;&amp; !$groups.contains($group.documentReference.toString()))
              #set ($discard = $toProcess.add($group.documentReference.toString()))
              #set ($discard = $groups.add($escapetool.sql($group.documentReference.toString())))
              #if ($groupObj.getProperty('studies').value.isEmpty() == false)
                #set ($discard = $studies.addAll($groupObj.getProperty('studies').value))
              #end
            #end
          #end
        #end
      #end
      #if ($studies.size() &gt; 0)
        $xwiki.jsx.use('PhenoTips.CreatePatientRecordForm')##
        $xwiki.ssx.use('PhenoTips.StudyBindingClass')##
        &lt;input type="hidden" name="studiesSheet" value="PhenoTips.StudyBindingSheet" /&gt;
      #end
    #end
    ##
    ## Project choosing section
    $xwiki.ssx.use('PhenoTips.ProjectBindingClass')##
    &lt;input type="hidden" name="projectsSheet" value="PhenoTips.ProjectBindingSheet" /&gt;
    ##
    ## Extensions displayed before the content
    #foreach ($e in $services.uix.getExtensions('org.phenotips.newPatientForm'))
      &lt;input type="hidden" name="$!e.parameters.name" value="$!e.parameters.value" /&gt;
    #end
    &lt;label for="create-patient-record"&gt;&lt;input type="submit" id="create-patient-record" value="$services.localization.render('phenotips.globalHeader.createPatient')"/&gt;&lt;/label&gt;
  &lt;/div&gt;&lt;/form&gt;
#end
{{/html}}{{/velocity}}</content>
  <object>
    <name>PhenoTips.CreatePatientRecordForm</name>
    <number>0</number>
    <className>XWiki.JavaScriptExtension</className>
    <guid>4a443a3a-0f92-471c-a251-a52ded8f604b</guid>
    <class>
      <name>XWiki.JavaScriptExtension</name>
      <customClass/>
      <customMapping/>
      <defaultViewSheet/>
      <defaultEditSheet/>
      <defaultWeb/>
      <nameField/>
      <validationScript/>
      <cache>
        <cache>0</cache>
        <disabled>0</disabled>
        <displayType>select</displayType>
        <multiSelect>0</multiSelect>
        <name>cache</name>
        <number>5</number>
        <prettyName>Caching policy</prettyName>
        <relationalStorage>0</relationalStorage>
        <separator> </separator>
        <separators>|, </separators>
        <size>1</size>
        <unmodifiable>0</unmodifiable>
        <values>long|short|default|forbid</values>
        <classType>com.xpn.xwiki.objects.classes.StaticListClass</classType>
      </cache>
      <code>
        <disabled>0</disabled>
        <name>code</name>
        <number>2</number>
        <prettyName>Code</prettyName>
        <rows>20</rows>
        <size>50</size>
        <unmodifiable>0</unmodifiable>
        <classType>com.xpn.xwiki.objects.classes.TextAreaClass</classType>
      </code>
      <name>
        <disabled>0</disabled>
        <name>name</name>
        <number>1</number>
        <prettyName>Name</prettyName>
        <size>30</size>
        <unmodifiable>0</unmodifiable>
        <classType>com.xpn.xwiki.objects.classes.StringClass</classType>
      </name>
      <parse>
        <disabled>0</disabled>
        <displayFormType>select</displayFormType>
        <displayType>yesno</displayType>
        <name>parse</name>
        <number>4</number>
        <prettyName>Parse content</prettyName>
        <unmodifiable>0</unmodifiable>
        <classType>com.xpn.xwiki.objects.classes.BooleanClass</classType>
      </parse>
      <use>
        <cache>0</cache>
        <disabled>0</disabled>
        <displayType>select</displayType>
        <multiSelect>0</multiSelect>
        <name>use</name>
        <number>3</number>
        <prettyName>Use this extension</prettyName>
        <relationalStorage>0</relationalStorage>
        <separator> </separator>
        <separators>|, </separators>
        <size>1</size>
        <unmodifiable>0</unmodifiable>
        <values>currentPage|onDemand|always</values>
        <classType>com.xpn.xwiki.objects.classes.StaticListClass</classType>
      </use>
    </class>
    <property>
      <cache>long</cache>
    </property>
    <property>
      <code>document.observe("xwiki:dom:loaded", function(event) {

   var newPatientForm = $('patient-creation-form');
   var studiesSectionInput = newPatientForm.down('input[name="studiesSheet"]');
   var projectsSectionInput = newPatientForm.down('input[name="projectsSheet"]');
   if (!newPatientForm || (!studiesSectionInput &amp;&amp; !projectsSectionInput)) {
     return;
   }

   var templateSelectionForm = new Element('form', {'action' : newPatientForm.action, 'class' : 'xform'});
   var formDataWrapper = new Element('div');
   templateSelectionForm.insert(formDataWrapper);

   if (projectsSectionInput) {
      if (studiesSectionInput) {
         var hr = new Element('hr');
         formDataWrapper.insert(hr);
      }
      var projectsSection = new Element('div');
      formDataWrapper.insert(projectsSection);
   }
   if (studiesSectionInput) {
      var studiesSection = new Element('div');
      formDataWrapper.insert(studiesSection);
   }

   newPatientForm.select('input[type="hidden"]').each(function(item) {
     if (item.name != 'sheet') {
         formDataWrapper.insert(new Element('input', {type : item.type, name: item.name, value: item.value}));
     }
   });
   var submitButton = new Element('input', {type : 'submit', value : "$services.localization.render('phenotips.chooseProjectStudy.createButton')", 'class' : 'button'});
   formDataWrapper.insert(submitButton);
   var cancelButton = new Element('input', {type : 'button', value : "$services.localization.render('phenotips.chooseProjectStudy.cancelButton')", 'class' : 'button secondary'});
   formDataWrapper.insert(' ').insert(cancelButton);
   var modalBox = new PhenoTips.widgets.ModalPopup(templateSelectionForm, false, {'title': "$services.localization.render('phenotips.chooseProjectStudy.popupTitle')", 'verticalPosition': 'top', 'removeOnClose': false});
   cancelButton.observe('click', function(event) {
     modalBox.closeDialog();
   });

   var onAjaxResponse = function(section) {
      return {
        onCreate : function() {
          section.update('&lt;img src="$xwiki.getSkinFile('icons/xwiki/ajax-loader-large.gif')"/&gt;');
          modalBox.showDialog();
        },
        onSuccess : function(response) {
           section.update(response.responseText);
        },
        onFailure : function(response) {
          var failureReason = response.responseText || response.statusText;
          if (response.statusText == '' /* No response */ || response.status == 12031 /* In IE */) {
             failureReason = "$services.localization.render('phenotips.chooseProjectStudy.failure.noResponse')";
          }
          _this._messages.update(new Element('div', {'class' : 'errormessage'}).update("$services.localization.render('phenotips.chooseProjectStudy.failureMessage')" + ' ' + failureReason));
        },
        on0 : function (response) {
          response.request.options.onFailure(response);
        }
      };
   };

   newPatientForm.observe('submit', function (event) {
     event.stop();

     var studiesDocRef, projectsDocRef;
     if (studiesSectionInput) {
        var studiesDocRef = XWiki.resource.get(studiesSectionInput.value, XWiki.EntityType.DOCUMENT);
        new Ajax.Request(new XWiki.Document(studiesDocRef.name, studiesDocRef.space).getURL('get'), onAjaxResponse(studiesSection));
     }

     if (projectsSectionInput) {
        var projectsDocRef = XWiki.resource.get(projectsSectionInput.value, XWiki.EntityType.DOCUMENT);
        new Ajax.Request(new XWiki.Document(projectsDocRef.name, projectsDocRef.space).getURL('get'), onAjaxResponse(projectsSection));
     }

   });
});</code>
    </property>
    <property>
      <name/>
    </property>
    <property>
      <parse>1</parse>
    </property>
    <property>
      <use>onDemand</use>
    </property>
  </object>
</xwikidoc>
