<?xml version="1.0" encoding="UTF-8"?>

<!--
 * See the NOTICE file distributed with this work for additional
 * information regarding copyright ownership.
 *
 * This is free software; you can redistribute it and/or modify it
 * under the terms of the GNU Lesser General Public License as
 * published by the Free Software Foundation; either version 2.1 of
 * the License, or (at your option) any later version.
 *
 * This software is distributed in the hope that it will be useful,
 * but WITHOUT ANY WARRANTY; without even the implied warranty of
 * MERCHANTABILITY or FITNESS FOR A PARTICULAR PURPOSE. See the GNU
 * Lesser General Public License for more details.
 *
 * You should have received a copy of the GNU Lesser General Public
 * License along with this software; if not, write to the Free
 * Software Foundation, Inc., 51 Franklin St, Fifth Floor, Boston, MA
 * 02110-1301 USA, or see the FSF site: http://www.fsf.org.
-->

<xwikidoc version="1.1">
  <web>PhenoTips</web>
  <name>ExportFilter</name>
  <language/>
  <defaultLanguage/>
  <translation>0</translation>
  <creator>xwiki:XWiki.Admin</creator>
  <creationDate>1414179462000</creationDate>
  <parent>PhenoTips.WebHome</parent>
  <author>xwiki:XWiki.Admin</author>
  <contentAuthor>xwiki:XWiki.Admin</contentAuthor>
  <date>1414179462000</date>
  <contentUpdateDate>1414179462000</contentUpdateDate>
  <version>1.1</version>
  <title/>
  <comment/>
  <minorEdit>false</minorEdit>
  <syntaxId>xwiki/2.1</syntaxId>
  <hidden>true</hidden>
  <content>{{velocity wiki="true"}}{{{
#macro (findPhenotypeMetadata)
  #set ($meta = $NULL)
  #foreach ($metaObj in $patientDoc.getObjects('PhenoTips.PhenotypeMetaClass'))
    #set ($nameProperty = $metaObj.get('target_property_name'))
    #set ($valueProperty = $metaObj.get('target_property_value'))
    #if ($nameProperty == $field &amp;&amp; $valueProperty == $code)
      #set ($meta = $metaObj)
      #break($foreach)
    #end
  #end
#end
##
##
#set ($targetClassName = 'PhenoTips.PatientClass')
#set ($ownerClassName = 'PhenoTips.OwnerClass')
#set ($targetClass = $xwiki.getClass($targetClassName))
#set ($activeFields = $services.recordConfiguration.activeConfiguration.enabledFieldNames)
#set ($dateFormat = $services.jodatime.getDateTimeFormatterForPattern('MM/dd/yyyy'))
#set ($query = ', BaseObject obj, LongProperty iid where doc.space = ? and obj.name = doc.fullName and obj.className = ? and iid.id.id = obj.id and iid.id.name = ''identifier'' and iid.value &gt;= 0')
#set ($parameters = ['data', $targetClassName])
#set ($isFirstReferrer = true)
#foreach ($referrer in $request.getParameterValues('doc.creator'))
  #if ($referrer != '')
    #if ($isFirstReferrer)
      #set ($query = $query.concat(' and ('))
      #set ($isFirstReferrer = false)
    #else
      #set ($query = $query.concat(' or '))
    #end
    #if ($referrer.contains(':'))
      #set ($query = $query.concat('doc.creator = ? or '))
      #set ($discard = $parameters.add($stringtool.substringAfter($referrer, ':')))
    #end
    #set ($query = $query.concat('doc.creator = ?'))
    #set ($discard = $parameters.add($referrer))
  #end
#end
#if (!$isFirstReferrer)
  #set ($query = $query.concat(')'))
#end
#set ($isFirstOwner = true)
#foreach ($owner in $request.getParameterValues('owner'))
  #if ($owner != '')
    #if ($isFirstOwner)
      #set ($query = $query.concat(' and ('))
      #set ($isFirstOwner = false)
    #else
      #set ($query = $query.concat(' or '))
    #end
    #set ($query = $query.concat('owner.value = ?'))
    #set ($discard = $parameters.add($services.model.resolveDocument($owner).toString()))
  #end
#end
#if (!$isFirstOwner)
  #set ($query = $query.concat(')'))
  #set ($query = ", BaseObject ownerobj, StringProperty owner" + $query + " and ownerobj.className = '$ownerClassName' and owner.name = 'owner' and owner.id.id=ownerobj.id and ownerobj.name = doc.fullName")
#end
#set ($isFirstAuthor = true)
#foreach ($author in $request.getParameterValues('doc.author'))
  #if ($author != '')
    #if ($isFirstAuthor)
      #set ($query = $query.concat(' and ('))
      #set ($isFirstAuthor = false)
    #else
      #set ($query = $query.concat(' or '))
    #end
    #if ($author.contains(':'))
      #set ($query = $query.concat('doc.author = ? or '))
      #set ($discard = $parameters.add($stringtool.substringAfter($author, ':')))
    #end
    #set ($query = $query.concat('doc.author = ?'))
    #set ($discard = $parameters.add($author))
  #end
#end
#if (!$isFirstAuthor)
  #set ($query = $query.concat(')'))
#end
#set ($isFirstPhenotype = true)
#set ($joinOperator = "$!{request.get('phenotype/join_mode').toUpperCase()}")
#if ($joinOperator != 'AND' &amp;&amp; $joinOperator != 'OR')
  #set ($joinOperator = 'AND')
#end
#foreach ($phenotype in $request.getParameterValues('phenotype'))
  #if ($phenotype != '')
    #if ($isFirstPhenotype)
      #set ($isFirstPhenotype = false)
      #if ("$!request.phenotype_subterms" == 'no')
        #set ($query = ", DBStringListProperty phenotype join phenotype.list as phenotypeValue ${query} and phenotype.id.id = obj.id and phenotype.id.name = 'phenotype' and (? in phenotypeValue")
      #else
        #set ($query = ", DBStringListProperty phenotype join phenotype.list as phenotypeValue ${query} and phenotype.id.id = obj.id and phenotype.id.name = 'extended_phenotype' and (? in phenotypeValue")
      #end
    #else
      #set ($query = $query.concat(" ${joinOperator} ? in phenotypeValue"))
    #end
    #set ($discard = $parameters.add($phenotype))
  #end
#end
#if (!$isFirstPhenotype)
  #set ($query = $query.concat(')'))
#end
#set ($isFirstDisease = true)
#set ($joinOperator = "$!{request.get('omim/join_mode').toUpperCase()}")
#if ($joinOperator != 'AND' &amp;&amp; $joinOperator != 'OR')
  #set ($joinOperator = 'AND')
#end
#foreach ($disease in $request.getParameterValues('omim_id'))
  #if ($disease != '')
    #if ($isFirstDisease)
      #set ($query = ", DBStringListProperty disease join disease.list as diseaseValue ${query} and disease.id.id = obj.id and disease.id.name = 'omim_id' and (? in diseaseValue")
      #set ($isFirstDisease = false)
    #else
      #set ($query = $query.concat(" ${joinOperator} ? in diseaseValue"))
    #end
    #set ($discard = $parameters.add($disease))
  #end
#end
#if (!$isFirstDisease)
  #set ($query = $query.concat(')'))
#end
#if ("$!request.get('doc.creationDate/after')" != '')
  #set ($date = $dateFormat.parseDateTime($request.get('doc.creationDate/after')))
  #set ($query = $query.concat(' and doc.creationDate &gt; ?'))
  #set ($discard = $parameters.add($date.toDate()))
#end
#if ("$!request.get('doc.creationDate/before')" != '')
  #set ($date = $dateFormat.parseDateTime($request.get('doc.creationDate/before')))
  #set ($query = $query.concat(' and doc.creationDate &lt; ?'))
  #set ($discard = $parameters.add($date.toDate()))
#end
#if ("$!request.get('doc.date/after')" != '')
  #set ($date = $dateFormat.parseDateTime($request.get('doc.date/after')))
  #set ($query = $query.concat(' and doc.date &gt; ?'))
  #set ($discard = $parameters.add($date.toDate()))
#end
#if ("$!request.get('doc.date/before')" != '')
  #set ($date = $dateFormat.parseDateTime($request.get('doc.date/before')))
  #set ($query = $query.concat(' and doc.date &lt; ?'))
  #set ($discard = $parameters.add($date.toDate()))
#end
#set ($hasBDate = false)
#if ("$!request.get('date_of_birth/after')" != '')
  #set ($date = $dateFormat.parseDateTime($request.get('date_of_birth/after')))
  #set ($query = ", DateProperty birthDate $query and birthDate.id.id = obj.id and birthDate.id.name = 'date_of_birth' and birthDate.value &gt; ?")
  #set ($discard = $parameters.add($date.toDate()))
  #set ($hasBDate = true)
#end
#if ("$!request.get('date_of_birth/before')" != '')
  #set ($date = $dateFormat.parseDateTime($request.get('date_of_birth/before')))
  #if ($hasBDate)
    #set ($query = "$query and birthDate.value &lt; ?")
  #else
    #set ($query = ", DateProperty birthDate $query and birthDate.id.id = obj.id and birthDate.id.name = 'date_of_birth' and birthDate.value &lt; ?")
  #end
  #set ($discard = $parameters.add($date.toDate()))
#end
#if ("$!request.get('external_id')" != '')
  #set ($query = ", StringProperty externalId $query and externalId.id.id = obj.id and externalId.id.name = 'external_id' and upper(externalId.value) like upper(?)")
  #set ($discard = $parameters.add("$request.get('external_id')%"))
#end
#set ($visibilities = $request.getParameterValues('visibility'))
#if ("$!visibilities" != '')
  #set ($query = ", StringProperty visibilityProperty, BaseObject visibilityObj $query and visibilityObj.name = doc.fullName and visibilityObj.className = 'PhenoTips.VisibilityClass' and visibilityProperty.id.id = visibilityObj.id and visibilityProperty.name = 'visibility' and (")
  #foreach ($visibility in $request.getParameterValues('visibility'))
    #if ($foreach.index == 0)
      #set ($query = "${query}visibilityProperty.value = ?")
    #else
      #set ($query = "${query} or visibilityProperty.value = ?")
    #end
    #set ($discard = $parameters.add($visibility))
  #end
  #set ($query = "${query})")
#else
  #set ($query = '')
#end
#if ($query != '')
  #set ($patientIds = $services.query.hql($query).bindValues($parameters))
  #set ($discard = $patientIds.addFilter('unique'))
  #if ($request.count)
    #set ($discard = $patientIds.addFilter('count'))
    $patientIds.execute()[0]
    #break
  #end
  #set ($patientIds = $patientIds.execute())
  #if ($request.list)
    $response.setContentType('application/json')
    $jsontool.serialize($patientIds)
    #break
  #end
#elseif ($request.count)
  0
  #break
#end
}}}
{{/velocity}}</content>
</xwikidoc>
